usdrate/__init__.py
usdrate/cli.py
usdrate-0.2.6.dist-info/METADATA
usdrate-0.2.6.dist-info/WHEEL
usdrate-0.2.6.dist-info/entry_points.txt
usdrate-0.2.6.dist-info/licenses/LICENSE
usdrate-0.2.6.dist-info/RECORD
