Metadata-Version: 2.4
Name: usdrate
Version: 0.2.6
Summary: usdrate is a lightweight CLI tool that retrieves and caches USD/JPY mid rate exchange data from 77bank's website. It automatically fetches data for the current and past 7 years, stores the results in a package-local cache, and allows you to easily query the mid rate for any specific date.
Author-email: kon0n0 <kono@ms1.kononet.jp>
License-Expression: MIT
License-File: LICENSE
Requires-Python: >=3.10
Requires-Dist: arrow>=1.3.0
Requires-Dist: beautifulsoup4
Requires-Dist: logflex>=0.1.7
Requires-Dist: pandas
Requires-Dist: requests
Requires-Dist: selenium>=4.29.0
